<!DOCTYPE suite SYSTEM "http://testng.org/testng-1.0.dtd">
<suite name="Beta Air" parallel="tests" thread-count="200" preserve-order="true">

<listeners>
		<listener class-name="org.uncommons.reportng.HTMLReporter" />
</listeners>
 
<!-- <test name="SanityCheck - B2C_Account" preserve-order="true">
    <classes>
      <class name="testScriptsB2CAccounts.B2CAccount_Login"/>
    </classes>
</test> 
 -->
<test name="B2CAir Sanity" preserve-order="true" parallel="true">
    <classes>
 	  <class name="testScriptsIndia.AirIntl_RT_Search_Results"/>
 	  <class name="testScriptsIndia.AirDom_RT_Search_Results"/>
 	  <class name="testScriptsIndia.AirDom_RT_SameDay_Search_Results"/>
 	  
 	  <class name="testScriptsIndia.AirDom_OW_SameDay_Search_Results"/>
 	  <class name="testScriptsIndia.AirDom_OW_SameDay_Search_Results"/>
 	  
 	  <class name="testScriptsIndia.AirDom_OW_Search_Results"/>
      
      <class name="testScriptsIndia.AirIntl_OW_Serach_Results"/>
      
      <class name="testScriptsIndia.ArIntl_MC_Serach_Results"/>
      <class name="testScriptsIndia.AirDom_OW_SRP_ModifySearch"/>
      <class name="testScriptsIndia.AirComDomLCCNoBaggageNBRetry"/>
      
 	<!--   <class name="testScriptsIndia.AirDom_OW_Prod_NBRetry"/>
 	  
 	  <class name="testScriptsIndia.AirCom_Dom_LCC_Airlines_Bookings"/>
 	  
      <class name="testScriptsIndia.AirDom_SplRT_LCC_Booking"/>
      <class name="testScriptsIndia.AirDom_SplRT_GDS_Booking"/>
       
      <class name="testScriptsIndia.SpecialRoundTripRateChecker"/>
       
 
      <class name="testScriptsIndia.AirCom_Dom_lcc_Insurance_Booking"/>
      <class name="testScriptsIndia.AirDom_OW_Coupon_Booking"/>
      
       
      <class name="testScriptsIndia.AirDom_RT_Coupon_Booking"/>
      <class name="testScriptsIndia.AirCom_Intl_OW_Coupon_Booking"/>
	  <class name="testScriptsIndia.AirCom_Intl_RT_Coupon_Booking"/>
	  
	  <class name="testScriptsIndia.AirCom_Dom_lcc_Insurance_Booking"/>
	  <class name="testScriptsIndia.AirCom_Intl_gds_Insurance_Booking"/>
	  
	  <class name="testScriptsIndia.AirDom_RT_SeatSelectionToBothSectors_SG_Booking"/>
	  <class name="testScriptsIndia.AirDom_RT_SeatSelectionToBothSectors_IndiGo_Booking"/>
	  
	  <class name="testScriptsIndia.AirDom_OW_IndiGo_AddMeal_Booking"/>
	  <class name="testScriptsIndia.AirDom_OW_GoAir_AddMeal_Booking"/>
	  
	  <class name="testScriptsIndia.AirCom_Dom_OW_SpiceJet_AddBaggage_Booking"/>
 	-->	
     	
    </classes>
</test>

<!-- <test name="CorpAir Sanity" preserve-order="true">
    <classes>
      <class name="testScriptsCorpIndia.AirCorpDomOWNBFailureCC"/>
    </classes>
</test>
 
<test name="MEAir Sanity" preserve-order="true">
    <classes>
    add cases of search results for OW, RT, MC for ME domain DOM and INTL searches
    	<class name="testScriptsMiddleEastAir.MEAir_Dom_Unsigned_MC_NB_Retry_Booking"/>
    	<class name="testScriptsMiddleEastAir.MEAir_SubDomain_BH_Generic_UI_Check"/>
    	<class name="testScriptsMiddleEastAir.MEAir_SubDomain_KW_Generic_UI_Check"/>
    	<class name="testScriptsMiddleEastAir.MEAir_SubDomain_OM_Generic_UI_Check"/>  
    	<class name="testScriptsMiddleEastAir.MEAir_SubDomain_QA_Generic_UI_Check"/>  
    	<class name="testScriptsMiddleEastAir.MEAir_SubDomain_SA_Generic_UI_Check"/>
       
    </classes>
</test>
 

<test name="AgencyAir Sanity" preserve-order="true">
    <classes>
      <class name="testScriptsAgency.AgencyAir_Dom_OneWay_NetBanking_Production"/>
    </classes>
</test> 
 -->
</suite> 